Workbook
Name age: #REF!
Name count: #REF!
Name FromArray_1: _xlfn.ANCHORARRAY(PivotTables!$E$117)
Name Slicer_Month: #N/A
Name Slicer_Subcategory: #N/A
Name worth: #REF!

Sheet Dashboard
U1: =IFERROR(GETPIVOTDATA("Sum of Amount",PivotTables!$B$22,"Cash Flow","Income"),0) -> 466700 | V1: =IFERROR(GETPIVOTDATA("Sum of Amount",PivotTables!$B$22,"Cash Flow","Income"),0) -> 466700
U2: =IFERROR(GETPIVOTDATA("Sum of Amount",PivotTables!$B$22,"Cash Flow","Expense"),0) -> 396351 | V2: =IFERROR(GETPIVOTDATA("Sum of Amount",PivotTables!$B$22,"Cash Flow","Expense"),0) -> 396351
U3: =IFERROR(GETPIVOTDATA("Sum of Amount",PivotTables!$B$22,"Cash Flow","Income"),0)-IFERROR(GETPIVOTDATA("Sum of Amount",PivotTables!$B$22,"Cash Flow","Expense"),0) -> 70349 | V3: =IFERROR(GETPIVOTDATA("Sum of Amount",PivotTables!$B$22,"Cash Flow","Income"),0)-IFERROR(GETPIVOTDATA("Sum of Amount",PivotTables!$B$22,"Cash Flow","Expense"),0) -> 70349
U5: {=_xlfn.IFS( PivotTables!E103>0,"Expenses are below budget, showing controlled essential spending.", PivotTables!E103<0,"Expenses exceeded the budget and may require review.", PivotTables!E103=0,"Expenses matched the budget exactly." )} -> Expenses are below budget, showing controlled essential spending.
U6: {=_xlfn.IFS( PivotTables!E102>0,"The value is above the target, showing a positive result.", PivotTables!E102<0,"The value is below the target, showing a negative result.", PivotTables!E102=0,"The value met the target exactly." )} -> The value is above the target, showing a positive result.
U7: {=_xlfn.IFS( PivotTables!E104>0,"You stayed within your budget, leaving more room for savings or essentials.", PivotTables!E104<0,"You spent more than planned on wants like dining out, shopping, or entertainment Etc.", PivotTables!E104=0,"Your wants spending is exactly aligned with your budget." )} -> You spent more than planned on wants like dining out, shopping, or entertainment Etc.
U9: =PivotTables!F115 -> Apr
U10: =PivotTables!G115 -> 48480
U11: =PivotTables!I115
U13: =PivotTables!H40 -> 0.23464051
U14: =PivotTables!I40 -> 93000
U15: ="of expenses spent on "&PivotTables!G40 -> of expenses spent on Rent / Mortgage
V17: =PivotTables!H85 -> 17500
U18: =PivotTables!G85 -> May | V18: =PivotTables!H86 -> 10000
U19: =PivotTables!G86 -> Jan
V20: =PivotTables!H69 -> 12250
U21: =PivotTables!G69 -> Jul | V21: =PivotTables!H70 -> 2392.5789
U22: =PivotTables!G70 -> Dec
V23: =PivotTables!H55 -> 7000
U24: =PivotTables!G55 -> Jan | V24: =PivotTables!H56 -> 250
U25: =PivotTables!G56 -> Apr

Sheet PivotTables
B3: Amount of Cash Flows by Month | C3: Expense | G3: =IFERROR(VLOOKUP(C1,$B$5:$C$14,2,FALSE()),"")
B4: Row Labels | C4: Expense | D4: Income | E4: Grand Total
B5: Apr | C5: 48480 | D5: 49200 | E5: 97680
B6: May | C6: 50226 | D6: 50000 | E6: 100226
B7: Jun | C7: 44191 | D7: 50000 | E7: 94191
B8: Jul | C8: 40959 | D8: 49000 | E8: 89959
B9: Aug | C9: 40459 | D9: 49000 | E9: 89459
B10: Sep | C10: 37459 | D10: 49000 | E10: 86459
B11: Oct | C11: 37659 | D11: 49000 | E11: 86659
B12: Nov | C12: 41459 | D12: 49000 | E12: 90459
B13: Dec | C13: 45459 | D13: 49000 | E13: 94459
B14: Jan | C14: 10000 | D14: 23500 | E14: 33500
B15: Grand Total | C15: 396351 | D15: 466700 | E15: 863051
B16: Balance | C16: =(SUM(D15-C15)/D15) -> 0.15073709 | D16: =1-C16 -> 0.84926291
B20: Month | C20: (All)
B22: Total Income/Expenses | C22: Sum of Amount
B23: Expense | C23: 396351 | D23: =GETPIVOTDATA("Sum of Amount",$B$22,"Cash Flow","Expense") -> 396351
B24: Income | C24: 466700 | D24: =GETPIVOTDATA("Sum of Amount",$B$22,"Cash Flow","Income") -> 466700
B25: Grand Total | C25: 863051
B26: Balance | C26: =C24-C23 -> 70349 | D26: =C26/C24 -> 0.15073709 | E26: =1-D26 -> 0.84926291
B27: Percent | C27: =C23/C24 -> 0.84926291 | D27: =IFERROR(C23/C24, "") -> 0.84926291
C28: =1-C27 -> 0.15073709
B31: Percentage by SubCategory | C31: Count of Subcategory | D31: Sum of Amount
B32: Financial Priority | C32: 0.38139535 | D32: 261681 | E32: =C32 -> 0.38139535 | F32: =1-E32 -> 0.61860465
B33: Needs | C33: 0.40930233 | D33: 109500 | E33: =C33 -> 0.40930233 | F33: =1-C33 -> 0.59069767
B34: Salary | C34: 0.17674419 | D34: 466700
B35: Wants | C35: 0.03255814 | D35: 25170 | E35: =C35 -> 0.03255814 | F35: =1-E35 -> 0.96744186
B36: Grand Total | C36: 1 | D36: 863051
B40: Total by Category | C40: Sum of Amount | E40: Total by Category | F40: Sum of Amount | G40: =E41 -> Rent / Mortgage | H40: =F41/C23 -> 0.23464051 | I40: =F41 -> 93000
B41: Car Maintenance | C41: 6000 | E41: Rent / Mortgage | F41: 93000
B42: School | C42: 7500 | E42: Groceries | F42: 81500
B43: Fuel | C43: 10000 | E43: Car Payment | F43: 74550
B44: Public Transport | C44: 10500 | E44: Loan | F44: 59168
B45: Other Expenses | C45: 25170 | E45: Utilities | F45: 28963
B46: Utilities | C46: 28963 | E46: Other Expenses | F46: 25170
B47: Loan | C47: 59168 | E47: Public Transport | F47: 10500
B48: Car Payment | C48: 74550 | E48: Fuel | F48: 10000
B49: Groceries | C49: 81500 | E49: School | F49: 7500
B50: Rent / Mortgage | C50: 93000 | E50: Car Maintenance | F50: 6000
B51: Grand Total | C51: 396351 | E51: Grand Total | F51: 396351
B55: Min Amount of Income/Expenses | C55: Column Labels | F55: Min Income | G55: =VLOOKUP(MIN(D57:D66),CHOOSE({1,2},D57:D66,B57:B66),2,FALSE) -> Jan | H55: =VLOOKUP(MIN(D57:D66),CHOOSE({1,2},D57:D66,B57:B66),1,FALSE) -> 7000
B56: Row Labels | C56: Expense | D56: Income | E56: Grand Total | F56: Min Expense | G56: =VLOOKUP(MIN(C57:C66),CHOOSE({1,2},C57:C66,B57:B66),2,FALSE) -> Apr | H56: =VLOOKUP(MIN(C57:C66),CHOOSE({1,2},C57:C66,B57:B66),1,FALSE) -> 250
B57: Jan | C57: 10000 | D57: 7000 | E57: 7000
B58: Apr | C58: 250 | D58: 7700 | E58: 250
B59: May | C59: 250 | D59: 8000 | E59: 250
B60: Jun | C60: 500 | D60: 8000 | E60: 500
B61: Jul | C61: 500 | D61: 8000 | E61: 500
B62: Aug | C62: 500 | D62: 8000 | E62: 500
B63: Sep | C63: 500 | D63: 8000 | E63: 500
B64: Oct | C64: 500 | D64: 8000 | E64: 500
B65: Nov | C65: 500 | D65: 8000 | E65: 500
B66: Dec | C66: 500 | D66: 8000 | E66: 500
B67: Grand Total | C67: 250 | D67: 7000 | E67: 250
B69: Average Amount of Income/Expenses | C69: Column Labels | F69: Average Income | G69: {=INDEX(B71:B80,MATCH(MIN(ABS(D71:D80-AVERAGE(D71:D80))),ABS(D71:D80-AVERAGE(D71:D80)),0))} -> Jul | H69: {=INDEX(D71:D80,MATCH(MIN(ABS(D71:D80-AVERAGE(D71:D80))),ABS(D71:D80-AVERAGE(D71:D80)),0))} -> 12250
B70: Row Labels | C70: Expense | D70: Income | E70: Grand Total | F70: Average Expense | G70: {=INDEX(B71:B80,MATCH(MIN(ABS(C71:C80-AVERAGE(C71:C80))),ABS(C71:C80-AVERAGE(C71:C80)),0))} -> Dec | H70: {=INDEX(C71:C80,MATCH(MIN(ABS(C71:C80-AVERAGE(C71:C80))),ABS(C71:C80-AVERAGE(C71:C80)),0))} -> 2392.5789
B71: Jan | C71: 10000 | D71: 11750 | E71: 11166.667
B72: Apr | C72: 2020 | D72: 12300 | E72: 3488.5714
B73: May | C73: 2283 | D73: 12500 | E73: 3854.8462
B74: Jun | C74: 2104.3333 | D74: 12500 | E74: 3767.64
B75: Jul | C75: 2047.95 | D75: 12250 | E75: 3748.2917
B76: Aug | C76: 2247.7222 | D76: 12250 | E76: 4066.3182
B77: Sep | C77: 2203.4706 | D77: 12250 | E77: 4117.0952
B78: Oct | C78: 2215.2353 | D78: 12250 | E78: 4126.619
B79: Nov | C79: 2303.2778 | D79: 12250 | E79: 4111.7727
B80: Dec | C80: 2392.5789 | D80: 12250 | E80: 4106.913
B81: Grand Total | C81: 2239.2712 | D81: 12281.579 | E81: 4014.1907
B84: Max Amount of Income/Expenses | C84: Column Labels
B85: Row Labels | C85: Expense | D85: Income | E85: Grand Total | F85: Max Income | G85: =INDEX(B86:B95,MATCH(MAX(D86:D95),D86:D95,0)) -> May | H85: =MAX(D86:D95) -> 17500
B86: Jan | C86: 10000 | D86: 16500 | E86: 16500 | F86: Max Expense | G86: =INDEX(B86:B95,MATCH(MAX(C86:C95),C86:C95,0)) -> Jan | H86: =MAX(C86:C95) -> 10000
B87: Apr | C87: 8500 | D87: 17000 | E87: 17000
B88: May | C88: 9000 | D88: 17500 | E88: 17500
B89: Jun | C89: 9000 | D89: 17500 | E89: 17500
B90: Jul | C90: 9000 | D90: 16500 | E90: 16500
B91: Aug | C91: 9000 | D91: 16500 | E91: 16500
B92: Sep | C92: 10000 | D92: 16500 | E92: 16500
B93: Oct | C93: 10000 | D93: 16500 | E93: 16500
B94: Nov | C94: 10000 | D94: 16500 | E94: 16500
B95: Dec | C95: 10000 | D95: 16500 | E95: 16500
B96: Grand Total | C96: 10000 | D96: 17500 | E96: 17500
B101: Row Labels | C101: Sum of Amount | D101: Sum of Actual | E101: Difference
B102: Financial Priority | C102: 261681 | D102: 260331 | E102: =C102-D102 -> 1350
B103: Needs | C103: 109500 | D103: 109289 | E103: =C103-D103 -> 211
B104: Wants | C104: 25170 | D104: 26670 | E104: =C104-D104 -> -1500
B105: Grand Total | C105: 396351 | D105: 396290
B107: Note:
B108: Needs | C108: {=_xlfn.IFS( E103>0,"Expenses are below budget, showing controlled essential spending.", E103<0,"Expenses exceeded the budget and may require review.", E103=0,"Expenses matched the budget exactly." )} -> Expenses are below budget, showing controlled essential spending.
B109: Financial Priorities | C109: {=_xlfn.IFS( E102>0,"The value is above the target, showing a positive result.", E102<0,"The value is below the target, showing a negative result.", E102=0,"The value met the target exactly." )} -> The value is above the target, showing a positive result.
B110: Wants | C110: {=_xlfn.IFS( E104>0,"You stayed within your budget, leaving more room for savings or essentials.", E104<0,"You spent more than planned on wants like dining out, shopping, or entertainment Etc.", E104=0,"Your wants spending is exactly aligned with your budget." )} -> You spent more than planned on wants like dining out, shopping, or entertainment Etc.
F114: =F115 & " Total Expenses" -> Apr Total Expenses
B115: Sum of Amount | C115: Column Labels | F115: =B130 -> Apr | G115: =IFERROR(VLOOKUP(F115,B117:C126,2,FALSE()),"") -> 48480 | H115: =IF(F115="Apr",0,IF(F115="May",VLOOKUP("Apr",B117:C126,2,0),IF(F115="Jun",VLOOKUP("May",B117:C126,2,0),IF(F115="Jul",VLOOKUP("Jun",B117:C126,2,0),IF(F115="Aug",VLOOKUP("Jul",B117:C126,2,0),IF(F115="Sep",VLOOKUP("Aug",B117:C126,2,0),IF(F115="Oct",VLOOKUP("Sep",B117:C126,2,0),IF(F115="Nov",VLOOKUP("Oct",B117:C126,2,0),IF(F115="Dec",VLOOKUP("Nov",B117:C126,2,0),IF(F115="Jan",VLOOKUP("Dec",B117:C126,2,0),0)))))))))) -> 0 | I115: =IF(H115=0,"",TEXT((G115-H115)/H115,"0.0%") & " (" & INT(G115-H115) & ")")
B116: Row Labels | C116: Expense | D116: Income | E116: Grand Total
B117: Jan | C117: 10000 | D117: 23500 | E117: 33500
B118: Apr | C118: 48480 | D118: 49200 | E118: 97680
B119: May | C119: 50226 | D119: 50000 | E119: 100226
B120: Jun | C120: 44191 | D120: 50000 | E120: 94191
B121: Jul | C121: 40959 | D121: 49000 | E121: 89959
B122: Aug | C122: 40459 | D122: 49000 | E122: 89459
B123: Sep | C123: 37459 | D123: 49000 | E123: 86459
B124: Oct | C124: 37659 | D124: 49000 | E124: 86659
B125: Nov | C125: 41459 | D125: 49000 | E125: 90459
...

Sheet Transactions END
B2: Date | C2: Month | D2: Cash Flow | E2: Category | F2: Amount | G2: Actual | H2: Subcategory | I2: Description (optional) | K2: Type | L2: Cash Flow | M2: Sub Type
B3: 46127 | C3: =TEXT(B3,"mmm") -> Apr | D3: =_xlfn.XLOOKUP(Table1[[#This Row],[Category]],Table2[Type],Table2[Cash Flow]) -> Income | E3: Dave Salary | F3: 16500 | G3: 17500 | H3: =_xlfn.XLOOKUP(Table1[[#This Row],[Category]],Table2[Type],Table2[Sub Type]) -> Salary | I3: Monthly salary | K3: Dave Salary | L3: Income | M3: Salary
B4: 46127 | C4: =TEXT(B4,"mmm") -> Apr | D4: =_xlfn.XLOOKUP(Table1[[#This Row],[Category]],Table2[Type],Table2[Cash Flow]) -> Income | E4: Cath Salary | F4: 8000 | G4: 8000 | H4: =_xlfn.XLOOKUP(Table1[[#This Row],[Category]],Table2[Type],Table2[Sub Type]) -> Salary | I4: Monthly salary | K4: Cath Salary | L4: Income | M4: Salary
B5: 46128 | C5: =TEXT(B5,"mmm") -> Apr | D5: =_xlfn.XLOOKUP(Table1[[#This Row],[Category]],Table2[Type],Table2[Cash Flow]) -> Expense | E5: Car Payment | F5: 1500 | G5: 1500 | H5: =_xlfn.XLOOKUP(Table1[[#This Row],[Category]],Table2[Type],Table2[Sub Type]) -> Financial Priority | I5: for March payment | K5: Interest / Dividends | L5: Income | M5: Additional
B6: 46128 | C6: =TEXT(B6,"mmm") -> Apr | D6: =_xlfn.XLOOKUP(Table1[[#This Row],[Category]],Table2[Type],Table2[Cash Flow]) -> Expense | E6: Rent / Mortgage | F6: 7000 | G6: 7000 | H6: =_xlfn.XLOOKUP(Table1[[#This Row],[Category]],Table2[Type],Table2[Sub Type]) -> Financial Priority | I6: House | K6: Gifts / Other | L6: Income | M6: Additional
B7: 46128 | C7: =TEXT(B7,"mmm") -> Apr | D7: =_xlfn.XLOOKUP(Table1[[#This Row],[Category]],Table2[Type],Table2[Cash Flow]) -> Expense | E7: Utilities | F7: 300 | G7: 300 | H7: =_xlfn.XLOOKUP(Table1[[#This Row],[Category]],Table2[Type],Table2[Sub Type]) -> Financial Priority | I7: Internet | K7: Rent / Mortgage | L7: Expense | M7: Financial Priority
B8: 46128 | C8: =TEXT(B8,"mmm") -> Apr | D8: =_xlfn.XLOOKUP(Table1[[#This Row],[Category]],Table2[Type],Table2[Cash Flow]) -> Expense | E8: Groceries | F8: 1000 | G8: 1000 | H8: =_xlfn.XLOOKUP(Table1[[#This Row],[Category]],Table2[Type],Table2[Sub Type]) -> Needs | I8: Milk | K8: Utilities | L8: Expense | M8: Financial Priority
B9: 46128 | C9: =TEXT(B9,"mmm") -> Apr | D9: =_xlfn.XLOOKUP(Table1[[#This Row],[Category]],Table2[Type],Table2[Cash Flow]) -> Expense | E9: Utilities | F9: 500 | G9: 500 | H9: =_xlfn.XLOOKUP(Table1[[#This Row],[Category]],Table2[Type],Table2[Sub Type]) -> Financial Priority | I9: Water | K9: Property Tax | L9: Expense | M9: Financial Priority
B10: 46128 | C10: =TEXT(B10,"mmm") -> Apr | D10: =_xlfn.XLOOKUP(Table1[[#This Row],[Category]],Table2[Type],Table2[Cash Flow]) -> Expense | E10: Loan | F10: 1060 | G10: 1060 | H10: =_xlfn.XLOOKUP(Table1[[#This Row],[Category]],Table2[Type],Table2[Sub Type]) -> Financial Priority | I10: Atome | K10: Household Goods | L10: Expense | M10: Needs
B11: 46128 | C11: =TEXT(B11,"mmm") -> Apr | D11: =_xlfn.XLOOKUP(Table1[[#This Row],[Category]],Table2[Type],Table2[Cash Flow]) -> Expense | E11: Groceries | F11: 2500 | G11: 2500 | H11: =_xlfn.XLOOKUP(Table1[[#This Row],[Category]],Table2[Type],Table2[Sub Type]) -> Needs | I11: Food | K11: Car Payment | L11: Expense | M11: Financial Priority
B12: 46128 | C12: =TEXT(B12,"mmm") -> Apr | D12: =_xlfn.XLOOKUP(Table1[[#This Row],[Category]],Table2[Type],Table2[Cash Flow]) -> Expense | E12: Public Transport | F12: 2000 | G12: 2000 | H12: =_xlfn.XLOOKUP(Table1[[#This Row],[Category]],Table2[Type],Table2[Sub Type]) -> Needs | I12: Cath transpo | K12: Fuel | L12: Expense | M12: Needs
B13: 46128 | C13: =TEXT(B13,"mmm") -> Apr | D13: =_xlfn.XLOOKUP(Table1[[#This Row],[Category]],Table2[Type],Table2[Cash Flow]) -> Expense | E13: Other Expenses | F13: 2670 | G13: 2670 | H13: =_xlfn.XLOOKUP(Table1[[#This Row],[Category]],Table2[Type],Table2[Sub Type]) -> Wants | I13: Parcel and lalamove and Proj. | K13: Public Transport | L13: Expense | M13: Needs
B14: 46128 | C14: =TEXT(B14,"mmm") -> Apr | D14: =_xlfn.XLOOKUP(Table1[[#This Row],[Category]],Table2[Type],Table2[Cash Flow]) -> Expense | E14: Loan | F14: 1000 | G14: 1000 | H14: =_xlfn.XLOOKUP(Table1[[#This Row],[Category]],Table2[Type],Table2[Sub Type]) -> Financial Priority | I14: Yhella | K14: Taxis & Other | L14: Expense | M14: Wants
... B17: 46128 | C17: =TEXT(B17,"mmm") -> Apr | D17: =_xlfn.XLOOKUP(Table1[[#This Row],[Category]],Table2[Type],Table2[Cash Flow]) -> Expense | E17: Loan | F17: 3470 | G17: 3470 | H17: =_xlfn.XLOOKUP(Table1[[#This Row],[Category]],Table2[Type],Table2[Sub Type]) -> Financial Priority | I17: unkown | K17: Medical Expenses | L17: Expense | M17: Needs
B18: 46142 | C18: =TEXT(B18,"mmm") -> Apr | D18: =_xlfn.XLOOKUP(Table1[[#This Row],[Category]],Table2[Type],Table2[Cash Flow]) -> Income | E18: Dave Salary | F18: 17000 | H18: =_xlfn.XLOOKUP(Table1[[#This Row],[Category]],Table2[Type],Table2[Sub Type]) -> Salary | K18: Supplements | L18: Expense | M18: Needs
B19: 46142 | C19: =TEXT(B19,"mmm") -> Apr | D19: =_xlfn.XLOOKUP(Table1[[#This Row],[Category]],Table2[Type],Table2[Cash Flow]) -> Income | E19: Cath Salary | F19: 7700 | H19: =_xlfn.XLOOKUP(Table1[[#This Row],[Category]],Table2[Type],Table2[Sub Type]) -> Salary | K19: Groceries | L19: Expense | M19: Needs
B20: 46142 | C20: =TEXT(B20,"mmm") -> Apr | D20: =_xlfn.XLOOKUP(Table1[[#This Row],[Category]],Table2[Type],Table2[Cash Flow]) -> Expense | E20: Loan | F20: 4000 | G20: 4000 | H20: =_xlfn.XLOOKUP(Table1[[#This Row],[Category]],Table2[Type],Table2[Sub Type]) -> Financial Priority | I20: mama | K20: Eating Out | L20: Expense | M20: Wants
B21: 46142 | C21: =TEXT(B21,"mmm") -> Apr | D21: =_xlfn.XLOOKUP(Table1[[#This Row],[Category]],Table2[Type],Table2[Cash Flow]) -> Expense | E21: Car Payment | F21: 8500 | G21: 8500 | H21: =_xlfn.XLOOKUP(Table1[[#This Row],[Category]],Table2[Type],Table2[Sub Type]) -> Financial Priority | I21: for March payment | K21: Entertainment | L21: Expense | M21: Wants
B22: 46142 | C22: =TEXT(B22,"mmm") -> Apr | D22: =_xlfn.XLOOKUP(Table1[[#This Row],[Category]],Table2[Type],Table2[Cash Flow]) -> Expense | E22: Loan | F22: 3460 | G22: 3460 | H22: =_xlfn.XLOOKUP(Table1[[#This Row],[Category]],Table2[Type],Table2[Sub Type]) -> Financial Priority | I22: ate for april | K22: Travel | L22: Expense | M22: Wants
B23: 46142 | C23: =TEXT(B23,"mmm") -> Apr | D23: =_xlfn.XLOOKUP(Table1[[#This Row],[Category]],Table2[Type],Table2[Cash Flow]) -> Expense | E23: Groceries | F23: 2500 | G23: 2500 | H23: =_xlfn.XLOOKUP(Table1[[#This Row],[Category]],Table2[Type],Table2[Sub Type]) -> Needs | I23: food | K23: Other Expenses | L23: Expense | M23: Wants
B24: 46142 | C24: =TEXT(B24,"mmm") -> Apr | D24: =_xlfn.XLOOKUP(Table1[[#This Row],[Category]],Table2[Type],Table2[Cash Flow]) -> Expense | E24: Groceries | F24: 1200 | G24: 1200 | H24: =_xlfn.XLOOKUP(Table1[[#This Row],[Category]],Table2[Type],Table2[Sub Type]) -> Needs | I24: Milk | K24: Loan | L24: Expense | M24: Financial Priority
B25: 46142 | C25: =TEXT(B25,"mmm") -> Apr | D25: =_xlfn.XLOOKUP(Table1[[#This Row],[Category]],Table2[Type],Table2[Cash Flow]) -> Expense | E25: Groceries | F25: 500 | G25: 500 | H25: =_xlfn.XLOOKUP(Table1[[#This Row],[Category]],Table2[Type],Table2[Sub Type]) -> Needs | I25: Diaper | K25: School | L25: Expense | M25: Needs
B26: 46142 | C26: =TEXT(B26,"mmm") -> Apr | D26: =_xlfn.XLOOKUP(Table1[[#This Row],[Category]],Table2[Type],Table2[Cash Flow]) -> Expense | E26: Utilities | F26: 1300 | G26: 1300 | H26: =_xlfn.XLOOKUP(Table1[[#This Row],[Category]],Table2[Type],Table2[Sub Type]) -> Financial Priority | I26: Kuryente | K26: Credit Card | L26: Expense | M26: Needs
B27: 46142 | C27: =TEXT(B27,"mmm") -> Apr | D27: =_xlfn.XLOOKUP(Table1[[#This Row],[Category]],Table2[Type],Table2[Cash Flow]) -> Expense | E27: Public Transport | F27: 1000 | G27: 1000 | H27: =_xlfn.XLOOKUP(Table1[[#This Row],[Category]],Table2[Type],Table2[Sub Type]) -> Needs | I27: Cath pamasahe sa trece | K27: Savings | L27: Savings | M27: Financial Priority
B28: 46142 | C28: =TEXT(B28,"mmm") -> Apr | D28: =_xlfn.XLOOKUP(Table1[[#This Row],[Category]],Table2[Type],Table2[Cash Flow]) -> Expense | E28: Utilities | F28: 250 | G28: 250 | H28: =_xlfn.XLOOKUP(Table1[[#This Row],[Category]],Table2[Type],Table2[Sub Type]) -> Financial Priority | I28: Internet
B29: 46142 | C29: =TEXT(B29,"mmm") -> Apr | D29: =_xlfn.XLOOKUP(Table1[[#This Row],[Category]],Table2[Type],Table2[Cash Flow]) -> Expense | E29: Loan | F29: 1000 | G29: 1000 | H29: =_xlfn.XLOOKUP(Table1[[#This Row],[Category]],Table2[Type],Table2[Sub Type]) -> Financial Priority | I29: Atome
B30: 46142 | C30: =TEXT(B30,"mmm") -> Apr | D30: =_xlfn.XLOOKUP(Table1[[#This Row],[Category]],Table2[Type],Table2[Cash Flow]) -> Expense | E30: Utilities | F30: 270 | G30: 270 | H30: =_xlfn.XLOOKUP(Table1[[#This Row],[Category]],Table2[Type],Table2[Sub Type]) -> Financial Priority | I30: Water
B31: 46157 | C31: =TEXT(B31,"mmm") -> May | D31: =_xlfn.XLOOKUP(Table1[[#This Row],[Category]],Table2[Type],Table2[Cash Flow]) -> Income | E31: Dave Salary | F31: 16500 | H31: =_xlfn.XLOOKUP(Table1[[#This Row],[Category]],Table2[Type],Table2[Sub Type]) -> Salary
B32: 46157 | C32: =TEXT(B32,"mmm") -> May | D32: =_xlfn.XLOOKUP(Table1[[#This Row],[Category]],Table2[Type],Table2[Cash Flow]) -> Income | E32: Cath Salary | F32: 8000 | H32: =_xlfn.XLOOKUP(Table1[[#This Row],[Category]],Table2[Type],Table2[Sub Type]) -> Salary
B33: 46157 | C33: =TEXT(B33,"mmm") -> May | D33: =_xlfn.XLOOKUP(Table1[[#This Row],[Category]],Table2[Type],Table2[Cash Flow]) -> Expense | E33: Rent / Mortgage | F33: 9000 | G33: 9000 | H33: =_xlfn.XLOOKUP(Table1[[#This Row],[Category]],Table2[Type],Table2[Sub Type]) -> Financial Priority | I33: House
B34: 46157 | C34: =TEXT(B34,"mmm") -> May | D34: =_xlfn.XLOOKUP(Table1[[#This Row],[Category]],Table2[Type],Table2[Cash Flow]) -> Expense | E34: Utilities | F34: 250 | G34: 250 | H34: =_xlfn.XLOOKUP(Table1[[#This Row],[Category]],Table2[Type],Table2[Sub Type]) -> Financial Priority | I34: Internet
B35: 46157 | C35: =TEXT(B35,"mmm") -> May | D35: =_xlfn.XLOOKUP(Table1[[#This Row],[Category]],Table2[Type],Table2[Cash Flow]) -> Expense | E35: Groceries | F35: 1500 | G35: 1489 | H35: =_xlfn.XLOOKUP(Table1[[#This Row],[Category]],Table2[Type],Table2[Sub Type]) -> Needs | I35: Milk
B36: 46157 | C36: =TEXT(B36,"mmm") -> May | D36: =_xlfn.XLOOKUP(Table1[[#This Row],[Category]],Table2[Type],Table2[Cash Flow]) -> Expense | E36: Utilities | F36: 1300 | G36: 1950 | H36: =_xlfn.XLOOKUP(Table1[[#This Row],[Category]],Table2[Type],Table2[Sub Type]) -> Financial Priority | I36: Kuryente
B37: 46157 | C37: =TEXT(B37,"mmm") -> May | D37: =_xlfn.XLOOKUP(Table1[[#This Row],[Category]],Table2[Type],Table2[Cash Flow]) -> Expense | E37: Public Transport | F37: 500 | G37: 200 | H37: =_xlfn.XLOOKUP(Table1[[#This Row],[Category]],Table2[Type],Table2[Sub Type]) -> Needs | I37: cath pamasahe sa trece
B38: 46157 | C38: =TEXT(B38,"mmm") -> May | D38: =_xlfn.XLOOKUP(Table1[[#This Row],[Category]],Table2[Type],Table2[Cash Flow]) -> Expense | E38: Groceries | F38: 2500 | G38: 3500 | H38: =_xlfn.XLOOKUP(Table1[[#This Row],[Category]],Table2[Type],Table2[Sub Type]) -> Needs | I38: Food
B39: 46157 | C39: =TEXT(B39,"mmm") -> May | D39: =_xlfn.XLOOKUP(Table1[[#This Row],[Category]],Table2[Type],Table2[Cash Flow]) -> Expense | E39: Groceries | F39: 500 | G39: 100 | H39: =_xlfn.XLOOKUP(Table1[[#This Row],[Category]],Table2[Type],Table2[Sub Type]) -> Needs | I39: Diaper
B40: 46157 | C40: =TEXT(B40,"mmm") -> May | D40: =_xlfn.XLOOKUP(Table1[[#This Row],[Category]],Table2[Type],Table2[Cash Flow]) -> Expense | E40: Loan | F40: 1166 | G40: 1166 | H40: =_xlfn.XLOOKUP(Table1[[#This Row],[Category]],Table2[Type],Table2[Sub Type]) -> Financial Priority | I40: Atome Cash
B41: 46157 | C41: =TEXT(B41,"mmm") -> May | D41: =_xlfn.XLOOKUP(Table1[[#This Row],[Category]],Table2[Type],Table2[Cash Flow]) -> Expense | E41: Groceries | F41: 500 | G41: 0 | H41: =_xlfn.XLOOKUP(Table1[[#This Row],[Category]],Table2[Type],Table2[Sub Type]) -> Needs | I41: Toiletries
B42: 46157 | C42: =TEXT(B42,"mmm") -> May | D42: =_xlfn.XLOOKUP(Table1[[#This Row],[Category]],Table2[Type],Table2[Cash Flow]) -> Expense | E42: Other Expenses | F42: 4500 | G42: 6000 | H42: =_xlfn.XLOOKUP(Table1[[#This Row],[Category]],Table2[Type],Table2[Sub Type]) -> Wants | I42: Macey bday
B43: 46157 | C43: =TEXT(B43,"mmm") -> May | D43: =_xlfn.XLOOKUP(Table1[[#This Row],[Category]],Table2[Type],Table2[Cash Flow]) -> Expense | E43: Fuel | F43: 1000 | G43: 1000 | H43: =_xlfn.XLOOKUP(Table1[[#This Row],[Category]],Table2[Type],Table2[Sub Type]) -> Needs | I43: Fuel
B44: 46157 | C44: =TEXT(B44,"mmm") -> May | D44: =_xlfn.XLOOKUP(Table1[[#This Row],[Category]],Table2[Type],Table2[Cash Flow]) -> Expense | E44: Loan | F44: 2000 | G44: 0 | H44: =_xlfn.XLOOKUP(Table1[[#This Row],[Category]],Table2[Type],Table2[Sub Type]) -> Financial Priority | I44: Mama
B45: 46172 | C45: =TEXT(B45,"mmm") -> May | D45: =_xlfn.XLOOKUP(Table1[[#This Row],[Category]],Table2[Type],Table2[Cash Flow]) -> Income | E45: Dave Salary | F45: 17500 | H45: =_xlfn.XLOOKUP(Table1[[#This Row],[Category]],Table2[Type],Table2[Sub Type]) -> Salary
B46: 46172 | C46: =TEXT(B46,"mmm") -> May | D46: =_xlfn.XLOOKUP(Table1[[#This Row],[Category]],Table2[Type],Table2[Cash Flow]) -> Income | E46: Cath Salary | F46: 8000 | H46: =_xlfn.XLOOKUP(Table1[[#This Row],[Category]],Table2[Type],Table2[Sub Type]) -> Salary
B47: 46172 | C47: =TEXT(B47,"mmm") -> May | D47: =_xlfn.XLOOKUP(Table1[[#This Row],[Category]],Table2[Type],Table2[Cash Flow]) -> Expense | E47: Car Payment | F47: 8550 | G47: 8550 | H47: =_xlfn.XLOOKUP(Table1[[#This Row],[Category]],Table2[Type],Table2[Sub Type]) -> Financial Priority | I47: For April payment
B48: 46172 | C48: =TEXT(B48,"mmm") -> May | D48: =_xlfn.XLOOKUP(Table1[[#This Row],[Category]],Table2[Type],Table2[Cash Flow]) -> Expense | E48: Car Payment | F48: 7000 | G48: 7000 | H48: =_xlfn.XLOOKUP(Table1[[#This Row],[Category]],Table2[Type],Table2[Sub Type]) -> Financial Priority | I48: For April payment
B49: 46172 | C49: =TEXT(B49,"mmm") -> May | D49: =_xlfn.XLOOKUP(Table1[[#This Row],[Category]],Table2[Type],Table2[Cash Flow]) -> Expense | E49: Loan | F49: 3460 | G49: 3460 | H49: =_xlfn.XLOOKUP(Table1[[#This Row],[Category]],Table2[Type],Table2[Sub Type]) -> Financial Priority | I49: Ate
B50: 46172 | C50: =TEXT(B50,"mmm") -> May | D50: =_xlfn.XLOOKUP(Table1[[#This Row],[Category]],Table2[Type],Table2[Cash Flow]) -> Expense | E50: School | F50: 1000 | G50: 1000 | H50: =_xlfn.XLOOKUP(Table1[[#This Row],[Category]],Table2[Type],Table2[Sub Type]) -> Needs | I50: Admission
B51: 46172 | C51: =TEXT(B51,"mmm") -> May | D51: =_xlfn.XLOOKUP(Table1[[#This Row],[Category]],Table2[Type],Table2[Cash Flow]) -> Expense | E51: Groceries | F51: 1500 | G51: 1500 | H51: =_xlfn.XLOOKUP(Table1[[#This Row],[Category]],Table2[Type],Table2[Sub Type]) -> Needs | I51: Milk
B52: 46172 | C52: =TEXT(B52,"mmm") -> May | D52: =_xlfn.XLOOKUP(Table1[[#This Row],[Category]],Table2[Type],Table2[Cash Flow]) -> Expense | E52: Groceries | F52: 500 | G52: 500 | H52: =_xlfn.XLOOKUP(Table1[[#This Row],[Category]],Table2[Type],Table2[Sub Type]) -> Needs | I52: Diaper
B53: 46172 | C53: =TEXT(B53,"mmm") -> May | D53: =_xlfn.XLOOKUP(Table1[[#This Row],[Category]],Table2[Type],Table2[Cash Flow]) -> Expense | E53: Utilities | F53: 500 | G53: 500 | H53: =_xlfn.XLOOKUP(Table1[[#This Row],[Category]],Table2[Type],Table2[Sub Type]) -> Financial Priority | I53: Water
B54: 46172 | C54: =TEXT(B54,"mmm") -> May | D54: =_xlfn.XLOOKUP(Table1[[#This Row],[Category]],Table2[Type],Table2[Cash Flow]) -> Expense | E54: Loan | F54: 2000 | G54: 2000 | H54: =_xlfn.XLOOKUP(Table1[[#This Row],[Category]],Table2[Type],Table2[Sub Type]) -> Financial Priority | I54: Atome Credit
B55: 46172 | C55: =TEXT(B55,"mmm") -> May | D55: =_xlfn.XLOOKUP(Table1[[#This Row],[Category]],Table2[Type],Table2[Cash Flow]) -> Expense | E55: Utilities | F55: 500 | G55: 500 | H55: =_xlfn.XLOOKUP(Table1[[#This Row],[Category]],Table2[Type],Table2[Sub Type]) -> Financial Priority | I55: Internet
B56: 46172 | C56: =TEXT(B56,"mmm") -> May | D56: =_xlfn.XLOOKUP(Table1[[#This Row],[Category]],Table2[Type],Table2[Cash Flow]) -> Expense | E56: Fuel | F56: 500 | G56: 500 | H56: =_xlfn.XLOOKUP(Table1[[#This Row],[Category]],Table2[Type],Table2[Sub Type]) -> Needs | I56: Fuel
B57: 46188 | C57: =TEXT(B57,"mmm") -> Jun | D57: =_xlfn.XLOOKUP(Table1[[#This Row],[Category]],Table2[Type],Table2[Cash Flow]) -> Income | E57: Dave Salary | F57: 17500 | H57: =_xlfn.XLOOKUP(Table1[[#This Row],[Category]],Table2[Type],Table2[Sub Type]) -> Salary
B58: 46188 | C58: =TEXT(B58,"mmm") -> Jun | D58: =_xlfn.XLOOKUP(Table1[[#This Row],[Category]],Table2[Type],Table2[Cash Flow]) -> Income | E58: Cath Salary | F58: 8000 | H58: =_xlfn.XLOOKUP(Table1[[#This Row],[Category]],Table2[Type],Table2[Sub Type]) -> Salary
B59: 46188 | C59: =TEXT(B59,"mmm") -> Jun | D59: =_xlfn.XLOOKUP(Table1[[#This Row],[Category]],Table2[Type],Table2[Cash Flow]) -> Expense | E59: Rent / Mortgage | F59: 9000 | G59: 9000 | H59: =_xlfn.XLOOKUP(Table1[[#This Row],[Category]],Table2[Type],Table2[Sub Type]) -> Financial Priority | I59: House
B60: 46188 | C60: =TEXT(B60,"mmm") -> Jun | D60: =_xlfn.XLOOKUP(Table1[[#This Row],[Category]],Table2[Type],Table2[Cash Flow]) -> Expense | E60: Utilities | F60: 899 | G60: 899 | H60: =_xlfn.XLOOKUP(Table1[[#This Row],[Category]],Table2[Type],Table2[Sub Type]) -> Financial Priority | I60: Internet
B61: 46188 | C61: =TEXT(B61,"mmm") -> Jun | D61: =_xlfn.XLOOKUP(Table1[[#This Row],[Category]],Table2[Type],Table2[Cash Flow]) -> Expense | E61: Groceries | F61: 1500 | G61: 1500 | H61: =_xlfn.XLOOKUP(Table1[[#This Row],[Category]],Table2[Type],Table2[Sub Type]) -> Needs | I61: Milk
B62: 46188 | C62: =TEXT(B62,"mmm") -> Jun | D62: =_xlfn.XLOOKUP(Table1[[#This Row],[Category]],Table2[Type],Table2[Cash Flow]) -> Expense | E62: Utilities | F62: 2000 | G62: 2000 | H62: =_xlfn.XLOOKUP(Table1[[#This Row],[Category]],Table2[Type],Table2[Sub Type]) -> Financial Priority | I62: Kuryente
B63: 46188 | C63: =TEXT(B63,"mmm") -> Jun | D63: =_xlfn.XLOOKUP(Table1[[#This Row],[Category]],Table2[Type],Table2[Cash Flow]) -> Expense | E63: Public Transport | F63: 500 | G63: 500 | H63: =_xlfn.XLOOKUP(Table1[[#This Row],[Category]],Table2[Type],Table2[Sub Type]) -> Needs | I63: cath pamasahe sa trece
B64: 46188 | C64: =TEXT(B64,"mmm") -> Jun | D64: =_xlfn.XLOOKUP(Table1[[#This Row],[Category]],Table2[Type],Table2[Cash Flow]) -> Expense | E64: Groceries | F64: 2500 | G64: 2500 | H64: =_xlfn.XLOOKUP(Table1[[#This Row],[Category]],Table2[Type],Table2[Sub Type]) -> Needs | I64: Food
B65: 46188 | C65: =TEXT(B65,"mmm") -> Jun | D65: =_xlfn.XLOOKUP(Table1[[#This Row],[Category]],Table2[Type],Table2[Cash Flow]) -> Expense | E65: Loan | F65: 1000 | G65: 1000 | H65: =_xlfn.XLOOKUP(Table1[[#This Row],[Category]],Table2[Type],Table2[Sub Type]) -> Financial Priority | I65: UB Credit
B66: 46188 | C66: =TEXT(B66,"mmm") -> Jun | D66: =_xlfn.XLOOKUP(Table1[[#This Row],[Category]],Table2[Type],Table2[Cash Flow]) -> Expense | E66: Groceries | F66: 500 | G66: 500 | H66: =_xlfn.XLOOKUP(Table1[[#This Row],[Category]],Table2[Type],Table2[Sub Type]) -> Needs | I66: Toiletries
B67: 46188 | C67: =TEXT(B67,"mmm") -> Jun | D67: =_xlfn.XLOOKUP(Table1[[#This Row],[Category]],Table2[Type],Table2[Cash Flow]) -> Expense | E67: Fuel | F67: 1000 | G67: 1000 | H67: =_xlfn.XLOOKUP(Table1[[#This Row],[Category]],Table2[Type],Table2[Sub Type]) -> Needs | I67: Fuel
B68: 46188 | C68: =TEXT(B68,"mmm") -> Jun | D68: =_xlfn.XLOOKUP(Table1[[#This Row],[Category]],Table2[Type],Table2[Cash Flow]) -> Expense | E68: Loan | F68: 2332 | G68: 2332 | H68: =_xlfn.XLOOKUP(Table1[[#This Row],[Category]],Table2[Type],Table2[Sub Type]) -> Financial Priority | I68: Atome Cash
B69: 46188 | C69: =TEXT(B69,"mmm") -> Jun | D69: =_xlfn.XLOOKUP(Table1[[#This Row],[Category]],Table2[Type],Table2[Cash Flow]) -> Expense | E69: Loan | F69: 2000 | G69: 2000 | H69: =_xlfn.XLOOKUP(Table1[[#This Row],[Category]],Table2[Type],Table2[Sub Type]) -> Financial Priority | I69: Mama
B70: 46188 | C70: =TEXT(B70,"mmm") -> Jun | D70: =_xlfn.XLOOKUP(Table1[[#This Row],[Category]],Table2[Type],Table2[Cash Flow]) -> Expense | E70: Other Expenses | F70: 2000 | G70: 2000 | H70: =_xlfn.XLOOKUP(Table1[[#This Row],[Category]],Table2[Type],Table2[Sub Type]) -> Wants | I70: School
B71: 46203 | C71: =TEXT(B71,"mmm") -> Jun | D71: =_xlfn.XLOOKUP(Table1[[#This Row],[Category]],Table2[Type],Table2[Cash Flow]) -> Income | E71: Dave Salary | F71: 16500 | H71: =_xlfn.XLOOKUP(Table1[[#This Row],[Category]],Table2[Type],Table2[Sub Type]) -> Salary
B72: 46203 | C72: =TEXT(B72,"mmm") -> Jun | D72: =_xlfn.XLOOKUP(Table1[[#This Row],[Category]],Table2[Type],Table2[Cash Flow]) -> Income | E72: Cath Salary | F72: 8000 | H72: =_xlfn.XLOOKUP(Table1[[#This Row],[Category]],Table2[Type],Table2[Sub Type]) -> Salary
B73: 46203 | C73: =TEXT(B73,"mmm") -> Jun | D73: =_xlfn.XLOOKUP(Table1[[#This Row],[Category]],Table2[Type],Table2[Cash Flow]) -> Expense | E73: Car Payment | F73: 7000 | G73: 7000 | H73: =_xlfn.XLOOKUP(Table1[[#This Row],[Category]],Table2[Type],Table2[Sub Type]) -> Financial Priority | I73: Updated payment
B74: 46203 | C74: =TEXT(B74,"mmm") -> Jun | D74: =_xlfn.XLOOKUP(Table1[[#This Row],[Category]],Table2[Type],Table2[Cash Flow]) -> Expense | E74: Loan | F74: 3460 | G74: 3460 | H74: =_xlfn.XLOOKUP(Table1[[#This Row],[Category]],Table2[Type],Table2[Sub Type]) -> Financial Priority | I74: Ate
B75: 46203 | C75: =TEXT(B75,"mmm") -> Jun | D75: =_xlfn.XLOOKUP(Table1[[#This Row],[Category]],Table2[Type],Table2[Cash Flow]) -> Expense | E75: Groceries | F75: 2500 | G75: 2500 | H75: =_xlfn.XLOOKUP(Table1[[#This Row],[Category]],Table2[Type],Table2[Sub Type]) -> Needs | I75: food
B76: 46203 | C76: =TEXT(B76,"mmm") -> Jun | D76: =_xlfn.XLOOKUP(Table1[[#This Row],[Category]],Table2[Type],Table2[Cash Flow]) -> Expense | E76: Groceries | F76: 1500 | G76: 1500 | H76: =_xlfn.XLOOKUP(Table1[[#This Row],[Category]],Table2[Type],Table2[Sub Type]) -> Needs | I76: Milk
B77: 46203 | C77: =TEXT(B77,"mmm") -> Jun | D77: =_xlfn.XLOOKUP(Table1[[#This Row],[Category]],Table2[Type],Table2[Cash Flow]) -> Expense | E77: Groceries | F77: 500 | G77: 500 | H77: =_xlfn.XLOOKUP(Table1[[#This Row],[Category]],Table2[Type],Table2[Sub Type]) -> Needs | I77: Diaper
B78: 46203 | C78: =TEXT(B78,"mmm") -> Jun | D78: =_xlfn.XLOOKUP(Table1[[#This Row],[Category]],Table2[Type],Table2[Cash Flow]) -> Expense | E78: Utilities | F78: 500 | G78: 500 | H78: =_xlfn.XLOOKUP(Table1[[#This Row],[Category]],Table2[Type],Table2[Sub Type]) -> Financial Priority | I78: Water
B79: 46203 | C79: =TEXT(B79,"mmm") -> Jun | D79: =_xlfn.XLOOKUP(Table1[[#This Row],[Category]],Table2[Type],Table2[Cash Flow]) -> Expense | E79: Public Transport | F79: 500 | G79: 500 | H79: =_xlfn.XLOOKUP(Table1[[#This Row],[Category]],Table2[Type],Table2[Sub Type]) -> Needs | I79: Cath pamasahe sa trece
B80: 46203 | C80: =TEXT(B80,"mmm") -> Jun | D80: =_xlfn.XLOOKUP(Table1[[#This Row],[Category]],Table2[Type],Table2[Cash Flow]) -> Expense | E80: Loan | F80: 2000 | G80: 2000 | H80: =_xlfn.XLOOKUP(Table1[[#This Row],[Category]],Table2[Type],Table2[Sub Type]) -> Financial Priority | I80: Clarisse
B81: 46203 | C81: =TEXT(B81,"mmm") -> Jun | D81: =_xlfn.XLOOKUP(Table1[[#This Row],[Category]],Table2[Type],Table2[Cash Flow]) -> Expense | E81: Fuel | F81: 1000 | G81: 1000 | H81: =_xlfn.XLOOKUP(Table1[[#This Row],[Category]],Table2[Type],Table2[Sub Type]) -> Needs | I81: Fuel
B82: 46218 | C82: =TEXT(B82,"mmm") -> Jul | D82: =_xlfn.XLOOKUP(Table1[[#This Row],[Category]],Table2[Type],Table2[Cash Flow]) -> Income | E82: Dave Salary | F82: 16500 | H82: =_xlfn.XLOOKUP(Table1[[#This Row],[Category]],Table2[Type],Table2[Sub Type]) -> Salary
B83: 46218 | C83: =TEXT(B83,"mmm") -> Jul | D83: =_xlfn.XLOOKUP(Table1[[#This Row],[Category]],Table2[Type],Table2[Cash Flow]) -> Income | E83: Cath Salary | F83: 8000 | H83: =_xlfn.XLOOKUP(Table1[[#This Row],[Category]],Table2[Type],Table2[Sub Type]) -> Salary
B84: 46218 | C84: =TEXT(B84,"mmm") -> Jul | D84: =_xlfn.XLOOKUP(Table1[[#This Row],[Category]],Table2[Type],Table2[Cash Flow]) -> Expense | E84: Rent / Mortgage | F84: 9000 | G84: 9000 | H84: =_xlfn.XLOOKUP(Table1[[#This Row],[Category]],Table2[Type],Table2[Sub Type]) -> Financial Priority | I84: House
B85: 46218 | C85: =TEXT(B85,"mmm") -> Jul | D85: =_xlfn.XLOOKUP(Table1[[#This Row],[Category]],Table2[Type],Table2[Cash Flow]) -> Expense | E85: Utilities | F85: 899 | G85: 899 | H85: =_xlfn.XLOOKUP(Table1[[#This Row],[Category]],Table2[Type],Table2[Sub Type]) -> Financial Priority | I85: Internet
B86: 46218 | C86: =TEXT(B86,"mmm") -> Jul | D86: =_xlfn.XLOOKUP(Table1[[#This Row],[Category]],Table2[Type],Table2[Cash Flow]) -> Expense | E86: Groceries | F86: 1800 | G86: 1800 | H86: =_xlfn.XLOOKUP(Table1[[#This Row],[Category]],Table2[Type],Table2[Sub Type]) -> Needs | I86: Milk
B87: 46218 | C87: =TEXT(B87,"mmm") -> Jul | D87: =_xlfn.XLOOKUP(Table1[[#This Row],[Category]],Table2[Type],Table2[Cash Flow]) -> Expense | E87: Utilities | F87: 2000 | G87: 2000 | H87: =_xlfn.XLOOKUP(Table1[[#This Row],[Category]],Table2[Type],Table2[Sub Type]) -> Financial Priority | I87: Kuryente
B88: 46218 | C88: =TEXT(B88,"mmm") -> Jul | D88: =_xlfn.XLOOKUP(Table1[[#This Row],[Category]],Table2[Type],Table2[Cash Flow]) -> Expense | E88: Public Transport | F88: 500 | G88: 500 | H88: =_xlfn.XLOOKUP(Table1[[#This Row],[Category]],Table2[Type],Table2[Sub Type]) -> Needs | I88: cath pamasahe sa trece
B89: 46218 | C89: =TEXT(B89,"mmm") -> Jul | D89: =_xlfn.XLOOKUP(Table1[[#This Row],[Category]],Table2[Type],Table2[Cash Flow]) -> Expense | E89: Groceries | F89: 500 | G89: 500 | H89: =_xlfn.XLOOKUP(Table1[[#This Row],[Category]],Table2[Type],Table2[Sub Type]) -> Needs | I89: Toiletries
B90: 46218 | C90: =TEXT(B90,"mmm") -> Jul | D90: =_xlfn.XLOOKUP(Table1[[#This Row],[Category]],Table2[Type],Table2[Cash Flow]) -> Expense | E90: Groceries | F90: 2500 | G90: 2500 | H90: =_xlfn.XLOOKUP(Table1[[#This Row],[Category]],Table2[Type],Table2[Sub Type]) -> Needs | I90: Food
B91: 46218 | C91: =TEXT(B91,"mmm") -> Jul | D91: =_xlfn.XLOOKUP(Table1[[#This Row],[Category]],Table2[Type],Table2[Cash Flow]) -> Expense | E91: Loan | F91: 2000 | G91: 2000 | H91: =_xlfn.XLOOKUP(Table1[[#This Row],[Category]],Table2[Type],Table2[Sub Type]) -> Financial Priority | I91: Clarisse
B92: 46218 | C92: =TEXT(B92,"mmm") -> Jul | D92: =_xlfn.XLOOKUP(Table1[[#This Row],[Category]],Table2[Type],Table2[Cash Flow]) -> Expense | E92: School | F92: 1500 | G92: 1500 | H92: =_xlfn.XLOOKUP(Table1[[#This Row],[Category]],Table2[Type],Table2[Sub Type]) -> Needs | I92: School
B93: 46218 | C93: =TEXT(B93,"mmm") -> Jul | D93: =_xlfn.XLOOKUP(Table1[[#This Row],[Category]],Table2[Type],Table2[Cash Flow]) -> Expense | E93: Loan | F93: 1000 | G93: 1000 | H93: =_xlfn.XLOOKUP(Table1[[#This Row],[Category]],Table2[Type],Table2[Sub Type]) -> Financial Priority | I93: Ate Feb balance
B94: 46234 | C94: =TEXT(B94,"mmm") -> Jul | D94: =_xlfn.XLOOKUP(Table1[[#This Row],[Category]],Table2[Type],Table2[Cash Flow]) -> Income | E94: Dave Salary | F94: 16500 | H94: =_xlfn.XLOOKUP(Table1[[#This Row],[Category]],Table2[Type],Table2[Sub Type]) -> Salary
B95: 46234 | C95: =TEXT(B95,"mmm") -> Jul | D95: =_xlfn.XLOOKUP(Table1[[#This Row],[Category]],Table2[Type],Table2[Cash Flow]) -> Income | E95: Cath Salary | F95: 8000 | H95: =_xlfn.XLOOKUP(Table1[[#This Row],[Category]],Table2[Type],Table2[Sub Type]) -> Salary
B96: 46234 | C96: =TEXT(B96,"mmm") -> Jul | D96: =_xlfn.XLOOKUP(Table1[[#This Row],[Category]],Table2[Type],Table2[Cash Flow]) -> Expense | E96: Car Payment | F96: 7000 | G96: 7000 | H96: =_xlfn.XLOOKUP(Table1[[#This Row],[Category]],Table2[Type],Table2[Sub Type]) -> Financial Priority | I96: Car update
B97: 46234 | C97: =TEXT(B97,"mmm") -> Jul | D97: =_xlfn.XLOOKUP(Table1[[#This Row],[Category]],Table2[Type],Table2[Cash Flow]) -> Expense | E97: Loan | F97: 3460 | G97: 3460 | H97: =_xlfn.XLOOKUP(Table1[[#This Row],[Category]],Table2[Type],Table2[Sub Type]) -> Financial Priority | I97: Ate
B98: 46234 | C98: =TEXT(B98,"mmm") -> Jul | D98: =_xlfn.XLOOKUP(Table1[[#This Row],[Category]],Table2[Type],Table2[Cash Flow]) -> Expense | E98: Groceries | F98: 2500 | G98: 2500 | H98: =_xlfn.XLOOKUP(Table1[[#This Row],[Category]],Table2[Type],Table2[Sub Type]) -> Needs | I98: food
B99: 46234 | C99: =TEXT(B99,"mmm") -> Jul | D99: =_xlfn.XLOOKUP(Table1[[#This Row],[Category]],Table2[Type],Table2[Cash Flow]) -> Expense | E99: Groceries | F99: 1800 | G99: 1800 | H99: =_xlfn.XLOOKUP(Table1[[#This Row],[Category]],Table2[Type],Table2[Sub Type]) -> Needs | I99: Milk
B100: 46234 | C100: =TEXT(B100,"mmm") -> Jul | D100: =_xlfn.XLOOKUP(Table1[[#This Row],[Category]],Table2[Type],Table2[Cash Flow]) -> Expense | E100: Groceries | F100: 500 | G100: 500 | H100: =_xlfn.XLOOKUP(Table1[[#This Row],[Category]],Table2[Type],Table2[Sub Type]) -> Needs | I100: Diaper
B101: 46234 | C101: =TEXT(B101,"mmm") -> Jul | D101: =_xlfn.XLOOKUP(Table1[[#This Row],[Category]],Table2[Type],Table2[Cash Flow]) -> Expense | E101: Utilities | F101: 500 | G101: 500 | H101: =_xlfn.XLOOKUP(Table1[[#This Row],[Category]],Table2[Type],Table2[Sub Type]) -> Financial Priority | I101: Water
B102: 46234 | C102: =TEXT(B102,"mmm") -> Jul | D102: =_xlfn.XLOOKUP(Table1[[#This Row],[Category]],Table2[Type],Table2[Cash Flow]) -> Expense | E102: Public Transport | F102: 500 | G102: 500 | H102: =_xlfn.XLOOKUP(Table1[[#This Row],[Category]],Table2[Type],Table2[Sub Type]) -> Needs | I102: Cath pamasahe sa trece
B103: 46234 | C103: =TEXT(B103,"mmm") -> Jul | D103: =_xlfn.XLOOKUP(Table1[[#This Row],[Category]],Table2[Type],Table2[Cash Flow]) -> Expense | E103: Loan | F103: 1000 | G103: 1000 | H103: =_xlfn.XLOOKUP(Table1[[#This Row],[Category]],Table2[Type],Table2[Sub Type]) -> Financial Priority | I103: Ate Feb balance
...

Sheet Quotes
A1: "Do the best you can until you know better. Then when you know better, do better." — Maya Angelou, Poet & Author | B1: {=INDEX(A1:A29,RANDBETWEEN(1,COUNTA(A1:A29)))} -> "When I dare to be powerful, to use my strength in the service of my vision, then it becomes less and less important whether I am afraid." — Audre Lorde, Poet & Civil Rights Activist
A2: "We must be impatient for change. Let us remember that our voice is a precious gift and we must use it." — Claudia Flores, Clinical Professor of Law at Yale Law School | B2: )
A3: "The only way you really see change, is by helping create it." — Lena Waithe, Emmy Award-Winning Writer & Producer
A4: "Do not allow people to dim your shine because they are blinded. Tell them to put on some sunglasses, because we were born this way." — Lady Gaga
A5: "Purpose is the essential element of you. It is the reason you are on the planet at this particular time in history." — Chadwick Boseman, Actor & Activist
A6: "The most difficult thing is the decision to act, the rest is merely tenacity." — Amelia Earhart, Aviation Pioneer
A7: "Ditch the dream and be a doer, not a dreamer." — Shonda Rhimes, Television Producer & Writer
A8: "Start where you are. Use what you have. Do what you can." — Arthur Ashe, Tennis Champion & Activist
A9: "What you do makes a difference, and you have to decide what kind of difference you want to make." — Jane Goodall, Primatologist & Conservationist
A10: "You have to write the book that wants to be written. And if the book will be too difficult for grown-ups, then you write it for children." — Madeleine L'Engle, Author
A11: "Courage is found in unlikely places." — Gildor Inglorion (character from The Lord of the Rings by J.R.R. Tolkien)
A12: "The most important step a person can take is always the next one." — Dalinar Kholin (character from The Stormlight Archive by Brandon Sanderson)
A13: "When I dare to be powerful, to use my strength in the service of my vision, then it becomes less and less important whether I am afraid." — Audre Lorde, Poet & Civil Rights Activist
A14: "A journey of a thousand li begins at one's feet." — Lao Tzu (Laozi), Ancient Chinese Philosopher
... A29: "You're braver than you believe, stronger than you seem, and smarter than you think." — Christopher Robin (character from Pooh's Grand Adventure)
